cooldfa/__init__.py
cooldfa/test.py
cooldfa/_core/core.py
cooldfa/_core/_ig_words/others.json
cooldfa/_core/_ig_words/politics.json
cooldfa/_core/_ig_words/sex.json
cooldfa/_core/_ig_words/url.json
cooldfa/_core/_ig_words/violence.json
cooldfa-1.1.1.dist-info/LICENSE
cooldfa-1.1.1.dist-info/WHEEL
cooldfa-1.1.1.dist-info/METADATA
cooldfa-1.1.1.dist-info/RECORD
