Metadata-Version: 2.1
Name: cooldfa
Version: 1.1.1
Summary: 基于 DFA 算法的敏感词检测器
Keywords: cooldfa,dfa
Author-email: "lcctoor.com" <lcctoor@outlook.com>
Classifier: License :: OSI Approved :: Apache Software License
Requires-Dist: arts>=2023.11.26
Project-URL: HomePage, https://github.com/lcctoor/arts/tree/main/arts/dfa
